{
  "domain": "greenfieldcolony.shopforsaleinfaridabad.com",
  "hero": {
    "title": "Prime Commercial Shops for Sale in Greenfield Colony Faridabad",
    "description": [
      "Greenfield Colony Faridabad is a premium and well-established residential locality known for its organized markets and strong purchasing capacity. Buyers searching for a shop for sale in Greenfield Colony Faridabad prefer this area due to its proximity to NH-19, Crown Plaza Mall, Badkhal Road, and nearby upscale residential pockets. The locality enjoys steady footfall from residents, office-goers, and daily visitors, making it commercially attractive.",
      "Shops for sale in Greenfield Colony Faridabad are well suited for medical stores, boutiques, cafes, salons, coaching centres, and professional service offices. As a mature locality with high-income households, businesses benefit from consistent daily sales and long-term customer retention. From an investment perspective, Greenfield Colony offers strong rental demand, low vacancy risk, and reliable appreciation, making it a preferred choice for commercial buyers and investors."
    ],
    "buttons": [
      {
        "label": "Browse Shops for Sale",
        "path": "/"
      },
      {
        "label": "Get Expert Assistance",
        "path": "/"
      }
    ],
    "images": [
      "https://plus.unsplash.com/premium_photo-1661954372617-15780178eb2e?w=500&auto=format&fit=crop&q=60",
      "https://plus.unsplash.com/premium_photo-1661883982941-50af7720a6ff?w=800&auto=format&fit=crop&q=60"
    ]
  },
  "featuresSection": {
    "heading": "Commercial Shop Size Options Available in Greenfield Colony",
    "description": [
      "Choosing the right shop size is important for efficient operations and customer comfort.",
      "Greenfield Colony Faridabad offers shops for sale across multiple plot sizes for diverse business needs."
    ],
    "features": [
      {
        "title": "4 Marla Plot Based Shops in Greenfield Colony",
        "description": "4 Marla shops are suitable for boutiques, salons, and specialised service outlets."
      },
      {
        "title": "6 Marla Plot Based Shops in Greenfield Colony",
        "description": "6 Marla shops provide better frontage and space, ideal for pharmacies and convenience stores."
      },
      {
        "title": "8 Marla Plot Based Shops in Greenfield Colony",
        "description": "8 Marla shops are ideal for clinics, cafes, and coaching centres with moderate footfall."
      },
      {
        "title": "10 Marla Plot Based Shops in Greenfield Colony",
        "description": "10 Marla shops suit restaurants, showrooms, and multi-service commercial setups."
      },
      {
        "title": "12 Marla Plot Based Shops in Greenfield Colony",
        "description": "12 Marla shops support premium brands, diagnostic centres, and professional offices."
      },
      {
        "title": "14 Marla Plot Based Shops in Greenfield Colony",
        "description": "14 Marla shops are premium assets offering high rental yield and capital appreciation."
      }
    ]
  },
  "locationsSection": {
    "title": "Explore Commercial and Residential Property Options Near Greenfield Colony",
    "description": [
      "Buyers exploring a shop for sale in Greenfield Colony Faridabad often look at nearby premium locations.",
      "These tiles help users easily navigate related property categories and surrounding areas."
    ],
    "locations": [
      {
        "title": "House For Sale",
        "path": "/",
        "icon": "Home"
      },
      {
        "title": "House For Rent",
        "path": "/",
        "icon": "Key"
      },
      {
        "title": "Flat For Sale",
        "path": "/",
        "icon": "Building2"
      },
      {
        "title": "Flat For Rent",
        "path": "/",
        "icon": "Building"
      },
      {
        "title": "Shop For Rent",
        "path": "/",
        "icon": "Store"
      },
      {
        "title": "Shop For Sale",
        "path": "/",
        "icon": "Store"
      },
      {
        "title": "Plot For Sale",
        "path": "/",
        "icon": "Landmark"
      },
      {
        "title": "Agriculture Land For Sale",
        "path": "/",
        "icon": "Tractor"
      },
      {
        "title": "To-Let Service",
        "path": "/",
        "icon": "Handshake"
      },
      {
        "title": "Commercial Property For Sale",
        "path": "/",
        "icon": "BriefcaseBusiness"
      }
    ]
  },
  "whyChoose": {
    "title": "Why Deal Acres Is Preferred for Buying Shops in Greenfield Colony",
    "description": [
      "Buying a shop for sale in Greenfield Colony Faridabad requires accurate market data and verified listings.",
      "Deal Acres is trusted for its transparency, professionalism, and buyer-first approach."
    ],
    "points": [
      {
        "title": "Verified Commercial Listings",
        "description": "Every shop listing is verified for ownership, approvals, and location accuracy."
      },
      {
        "title": "Premium Market Understanding",
        "description": "Strong knowledge of Greenfield Colony’s high-demand commercial environment."
      },
      {
        "title": "Transparent Pricing",
        "description": "Clear and honest pricing without hidden charges."
      },
      {
        "title": "High Rental Yield Focus",
        "description": "Properties shortlisted based on rental stability and tenant demand."
      },
      {
        "title": "Easy Property Search Experience",
        "description": "Simple and user-friendly interface for quick comparisons."
      },
      {
        "title": "End-to-End Buying Support",
        "description": "Complete assistance from property search to final registration."
      },
      {
        "title": "Legal and Documentation Support",
        "description": "Help with due diligence, agreements, and compliance."
      },
      {
        "title": "Trusted by Buyers and Investors",
        "description": "Preferred platform for commercial investments in Faridabad."
      }
    ]
  },
  "faqSection": {
    "title": "Frequently Asked Questions About Shops in Greenfield Colony Faridabad",
    "description": "Clear answers to common buyer queries for confident decision-making.",
    "faqs": [
      {
        "question": "Is Greenfield Colony a good location to buy a shop?",
        "answer": "Yes, it is a premium locality with strong purchasing power and steady footfall."
      },
      {
        "question": "What businesses perform best in Greenfield Colony?",
        "answer": "Medical stores, cafes, boutiques, salons, and service-based businesses perform well."
      },
      {
        "question": "Are shops in Greenfield Colony good for rental income?",
        "answer": "Yes, demand from local residents ensures stable and long-term rentals."
      },
      {
        "question": "Which shop size is suitable for small businesses?",
        "answer": "4 Marla and 6 Marla shops are ideal for small and mid-sized operations."
      },
      {
        "question": "Are bank loans available for buying shops here?",
        "answer": "Most approved commercial properties are eligible for bank financing."
      },
      {
        "question": "Is parking available near shops?",
        "answer": "Parking availability depends on shop frontage and road width."
      },
      {
        "question": "Are listings on Deal Acres legally verified?",
        "answer": "Yes, all properties go through legal and ownership checks."
      },
      {
        "question": "Is Greenfield Colony suitable for long-term investment?",
        "answer": "Yes, limited supply and premium demand support appreciation."
      },
      {
        "question": "Is resale easy for shops in Greenfield Colony?",
        "answer": "Strong buyer interest makes resale relatively smooth."
      },
      {
        "question": "How can I find the best shop for sale in Greenfield Colony Faridabad?",
        "answer": "Submit your requirements to receive verified and curated shop options."
      }
    ]
  },
  "contactSection": {
    "title": "Get in Touch for Shops for Sale in Greenfield Colony Faridabad",
    "description": [
      "Finding the right shop for sale in Greenfield Colony Faridabad becomes easy with expert guidance.",
      "Share your details to receive customised commercial property options matching your goals and budget."
    ],
    "formFields": [
      "name",
      "phone",
      "email",
      "message"
    ]
  }
}